skiearn/__init__.py
skiearn/viewer.py
skiearn/docs/01_data_preparation.txt
skiearn/docs/02_statistics_distributions.txt
skiearn/docs/03_hypothesis_testing.txt
skiearn/docs/04_causality_features.txt
skiearn/docs/05_outliers_robust.txt
skiearn/docs/06_supervised_learning.txt
skiearn/docs/07_model_evaluation.txt
skiearn/docs/08_imbalanced_missing.txt
skiearn/docs/09_explainability_viz.txt
skiearn/docs/10_dimensionality_clustering.txt
skiearn/docs/11_advanced_topics.txt
skiearn/docs/12_encoding_validation.txt
skiearn/docs/13_exam_traps.txt
skiearn/docs/CLASSIFICATION.txt
skiearn/docs/README.txt
skiearn/docs/STUDY_GUIDE.txt
skiearn/docs/VERIFICATION_COMPLETE.txt
skiearn/docs/doc1.txt
skiearn_kdd-1.0.4.dist-info/licenses/LICENSE
skiearn_kdd-1.0.4.dist-info/METADATA
skiearn_kdd-1.0.4.dist-info/WHEEL
skiearn_kdd-1.0.4.dist-info/top_level.txt
skiearn_kdd-1.0.4.dist-info/RECORD
