Metadata-Version: 2.4
Name: skiearn-kdd
Version: 1.0.4
Summary: Interactive Knowledge Discovery & Data Mining (KDD) study guide with comprehensive documentation
Home-page: https://github.com/yourusername/skiearn
Author: KDD Study Team
License: MIT
Project-URL: Homepage, https://github.com/yourusername/skiearn
Project-URL: Documentation, https://github.com/yourusername/skiearn
Project-URL: Repository, https://github.com/yourusername/skiearn
Project-URL: Bug Tracker, https://github.com/yourusername/skiearn/issues
Keywords: kdd,data-mining,machine-learning,statistics,study-guide,education,data-science
Classifier: Development Status :: 5 - Production/Stable
Classifier: Intended Audience :: Education
Classifier: Intended Audience :: Science/Research
Classifier: Topic :: Education
Classifier: Topic :: Scientific/Engineering :: Artificial Intelligence
Classifier: Topic :: Scientific/Engineering :: Information Analysis
Classifier: License :: OSI Approved :: MIT License
Classifier: Programming Language :: Python :: 3
Classifier: Programming Language :: Python :: 3.7
Classifier: Programming Language :: Python :: 3.8
Classifier: Programming Language :: Python :: 3.9
Classifier: Programming Language :: Python :: 3.10
Classifier: Programming Language :: Python :: 3.11
Classifier: Programming Language :: Python :: 3.12
Requires-Python: >=3.7
License-File: LICENSE
Dynamic: home-page
Dynamic: license-file
Dynamic: requires-python
